[{
		"filename":	"gfx/tile7.png",
		"x":	0,
		"y":	0,
		"w":	64,
		"h":	64,
		"rotated":	0
	}, {
		"filename":	"gfx/tile2.png",
		"x":	65,
		"y":	0,
		"w":	64,
		"h":	64,
		"rotated":	0
	}, {
		"filename":	"gfx/block.png",
		"x":	130,
		"y":	0,
		"w":	64,
		"h":	64,
		"rotated":	0
	}, {
		"filename":	"gfx/tile3.png",
		"x":	0,
		"y":	65,
		"w":	64,
		"h":	64,
		"rotated":	0
	}, {
		"filename":	"gfx/tile1.png",
		"x":	65,
		"y":	65,
		"w":	64,
		"h":	64,
		"rotated":	0
	}, {
		"filename":	"gfx/tile4.png",
		"x":	130,
		"y":	65,
		"w":	64,
		"h":	64,
		"rotated":	0
	}, {
		"filename":	"gfx/tile6.png",
		"x":	0,
		"y":	130,
		"w":	64,
		"h":	64,
		"rotated":	0
	}, {
		"filename":	"gfx/tile5.png",
		"x":	65,
		"y":	130,
		"w":	64,
		"h":	64,
		"rotated":	0
	}, {
		"filename":	"gfx/pete02.png",
		"x":	195,
		"y":	0,
		"w":	36,
		"h":	48,
		"rotated":	0
	}, {
		"filename":	"gfx/pete01.png",
		"x":	195,
		"y":	65,
		"w":	36,
		"h":	48,
		"rotated":	0
	}, {
		"filename":	"gfx/platform.png",
		"x":	130,
		"y":	130,
		"w":	124,
		"h":	34,
		"rotated":	0
	}, {
		"filename":	"gfx/pizza.png",
		"x":	130,
		"y":	165,
		"w":	25,
		"h":	27,
		"rotated":	0
	}]